tclwrapper/__init__.py
tclwrapper/tclutil.py
tclwrapper/tclwrapper.py
tclwrapper-0.0.1.dist-info/LICENSE.txt
tclwrapper-0.0.1.dist-info/METADATA
tclwrapper-0.0.1.dist-info/WHEEL
tclwrapper-0.0.1.dist-info/top_level.txt
tclwrapper-0.0.1.dist-info/RECORD
