Metadata-Version: 2.1
Name: tclwrapper
Version: 0.0.1
Summary: Python wrapper for programs that expose a tcl interface
Home-page: https://github.com/csail-csg/tclwrapper
Author: CSAIL CSG
Author-email: acwright@mit.edu
License: UNKNOWN
Keywords: TCL Wrapper tclsh wish
Platform: UNKNOWN
Classifier: Development Status :: 3 - Alpha
Classifier: Intended Audience :: Developers
Classifier: Topic :: Software Development :: Build Tools
Classifier: Programming Language :: Tcl
Classifier: License :: OSI Approved :: MIT License
Classifier: Programming Language :: Python :: 3.5
Classifier: Programming Language :: Python :: 3.6
